AUTHORS.rst
CONTRIBUTING.rst
HISTORY.rst
LICENSE
MANIFEST.in
README.md
requirements.txt
setup.cfg
setup.py
aioouimeaux/__init__.py
aioouimeaux/__main__.py
aioouimeaux/discovery.py
aioouimeaux/subscribe.py
aioouimeaux/utils.py
aioouimeaux/wemo.py
aioouimeaux.egg-info/PKG-INFO
aioouimeaux.egg-info/SOURCES.txt
aioouimeaux.egg-info/dependency_links.txt
aioouimeaux.egg-info/not-zip-safe
aioouimeaux.egg-info/requires.txt
aioouimeaux.egg-info/top_level.txt
aioouimeaux/__pycache__/__init__.cpython-36.pyc
aioouimeaux/__pycache__/__main__.cpython-36.pyc
aioouimeaux/__pycache__/discovery.cpython-36.pyc
aioouimeaux/__pycache__/subscribe.cpython-36.pyc
aioouimeaux/__pycache__/utils.cpython-36.pyc
aioouimeaux/__pycache__/wemo.cpython-36.pyc
aioouimeaux/device/__init__.py
aioouimeaux/device/bridge.py
aioouimeaux/device/insight.py
aioouimeaux/device/lightswitch.py
aioouimeaux/device/maker.py
aioouimeaux/device/motion.py
aioouimeaux/device/switch.py
aioouimeaux/device/__pycache__/__init__.cpython-36.pyc
aioouimeaux/device/__pycache__/bridge.cpython-36.pyc
aioouimeaux/device/__pycache__/insight.cpython-36.pyc
aioouimeaux/device/__pycache__/lightswitch.cpython-36.pyc
aioouimeaux/device/__pycache__/maker.cpython-36.pyc
aioouimeaux/device/__pycache__/motion.cpython-36.pyc
aioouimeaux/device/__pycache__/switch.cpython-36.pyc
aioouimeaux/device/api/__init__.py
aioouimeaux/device/api/service.py
aioouimeaux/device/api/__pycache__/__init__.cpython-36.pyc
aioouimeaux/device/api/__pycache__/service.cpython-36.pyc
aioouimeaux/device/api/xsd/__init__.py
aioouimeaux/device/api/xsd/device.py
aioouimeaux/device/api/xsd/device.xsd
aioouimeaux/device/api/xsd/service.py
aioouimeaux/device/api/xsd/service.xsd
aioouimeaux/device/api/xsd/__pycache__/__init__.cpython-36.pyc
aioouimeaux/device/api/xsd/__pycache__/device.cpython-36.pyc
aioouimeaux/device/api/xsd/__pycache__/service.cpython-36.pyc
aioouimeaux/examples/Randomize.py
aioouimeaux/examples/__init__.py
aioouimeaux/examples/watch.py
tests/__init__.py
tests/test_ouimeaux.py