Metadata-Version: 1.2
Name: aioouimeaux
Version: 0.1.0b5
Summary: Open source control for Belkin WeMo devices
Home-page: https://github.com/frawau/aioouimeaux
Author: François Wautier
Author-email: francois@wautier.eu
License: BSD
Download-URL: https://github.com/frawau/aioouimeaux/archive/0.1.0b5.tar.gz
Keywords: aioouimeaux WeMo automation
Platform: UNKNOWN
Classifier: Development Status :: 4 - Beta
Classifier: Topic :: Home Automation
Classifier: Intended Audience :: Developers
Classifier: License :: OSI Approved :: BSD License
Classifier: Natural Language :: English
Classifier: Programming Language :: Python :: 3.5
Classifier: Programming Language :: Python :: 3.6
Requires-Python: >=3.5
